pyprpaper/__init__.py
pyprpaper/pyprpaper.py
pyprpaper-0.3.2.dist-info/METADATA
pyprpaper-0.3.2.dist-info/WHEEL
pyprpaper-0.3.2.dist-info/entry_points.txt
pyprpaper-0.3.2.dist-info/licenses/LICENSE
pyprpaper-0.3.2.dist-info/RECORD
