Metadata-Version: 2.3
Name: pyprpaper
Version: 0.3.2
Summary: Randomly change wallpaper for given monitor(s) in hyprpaper.
Project-URL: Homepage, https://github.com/rofe33/pyprpaper
Project-URL: Issues, https://github.com/rofe33/pyprpaper/issues
Author-email: Raphael Tannous <raphaeltannous@proton.me>
License:                     GNU GENERAL PUBLIC LICENSE
License-File: LICENSE
Keywords: hyprland,hyprpaper,pyprpaper
Classifier: Development Status :: 4 - Beta
Requires-Python: >=3.8
